torchview/__init__.py
torchview/computation_graph.py
torchview/py.typed
torchview/recorder_tensor.py
torchview/torchview.py
torchview/utils.py
torchview/computation_node/__init__.py
torchview/computation_node/base_node.py
torchview/computation_node/compute_node.py
torchview-0.2.7.dist-info/licenses/LICENSE
torchview-0.2.7.dist-info/WHEEL
torchview-0.2.7.dist-info/METADATA
torchview-0.2.7.dist-info/RECORD
