Metadata-Version: 2.4
Name: torchview
Version: 0.2.7
Summary: Visualization of Pytorch Models
Keywords: pytorch,visualization,keras,torch,deep learning,machine learning,ml,neural network
Author: Mert Kurttutan
Author-email: kurttutan.mert@gmail.com
Maintainer-email: Mert Kurttutan <kurttutan.mert@gmail.com>
Requires-Python: >=3.8
Classifier: License :: OSI Approved :: MIT License
Classifier: Programming Language :: Python :: 3
Classifier: Programming Language :: Python :: 3.8
Classifier: Programming Language :: Python :: 3.9
Classifier: Programming Language :: Python :: 3.10
Classifier: Programming Language :: Python :: 3.11
License-File: LICENSE
Requires-Dist: graphviz
Requires-Dist: black ; extra == "dev"
Requires-Dist: codecov ; extra == "dev"
Requires-Dist: ruff==0.0.246 ; extra == "dev"
Requires-Dist: isort ; extra == "dev"
Requires-Dist: mypy ; extra == "dev"
Requires-Dist: pycln ; extra == "dev"
Requires-Dist: pylint ; extra == "dev"
Requires-Dist: pytest ; extra == "dev"
Requires-Dist: pytest-cov ; extra == "dev"
Requires-Dist: pre-commit ; extra == "dev"
Requires-Dist: packaging ; extra == "dev"
Requires-Dist: mkdocs ; extra == "dev"
Requires-Dist: mkdocs-material ; extra == "dev"
Requires-Dist: mkdocs-redirects ; extra == "dev"
Requires-Dist: mdformat ; extra == "dev"
Requires-Dist: mdformat-mkdocs ; extra == "dev"
Requires-Dist: mkdocs-gen-files ; extra == "dev"
Requires-Dist: mkdocstrings ; extra == "dev"
Requires-Dist: mkdocstrings-python ; extra == "dev"
Project-URL: homepage, https://github.com/mert-kurttutan/torchview
Project-URL: repository, https://github.com/mert-kurttutan/torchview
Provides-Extra: dev
